IO/__init__.py
IO/affichage.py
IO/export.py
core/__init__.py
core/analyseur.py
core/simulateur.py
models/__init__.py
models/reseau.py
models/route.py
models/vehicule.py
simulateur_trafic_gh-1.0.2.dist-info/licenses/LICENSE
tests/__init__.py
tests/conftest.py
tests/test_reseau.py
tests/test_route.py
tests/test_simulateur.py
tests/test_vehicule.py
simulateur_trafic_gh-1.0.2.dist-info/METADATA
simulateur_trafic_gh-1.0.2.dist-info/WHEEL
simulateur_trafic_gh-1.0.2.dist-info/top_level.txt
simulateur_trafic_gh-1.0.2.dist-info/RECORD
