Metadata-Version: 2.4
Name: simulateur_trafic_gh
Version: 1.0.2
Summary: Simulateur de trafic routier (routes, véhicules, réseau, analyse)
Home-page: https://github.com/YosraGhanmi/simulateur_trafic_gh.git
Author: yosr.gh
Author-email: yosraghanmi23@gmail.com
License: MIT
Classifier: Programming Language :: Python :: 3
Classifier: License :: OSI Approved :: MIT License
Classifier: Operating System :: OS Independent
Requires-Python: >=3.8
License-File: LICENSE
Dynamic: license-file
